LICENSE
MANIFEST.in
README.rst
requirements-dev.txt
setup.py
django_thumborize.egg-info/PKG-INFO
django_thumborize.egg-info/SOURCES.txt
django_thumborize.egg-info/dependency_links.txt
django_thumborize.egg-info/requires.txt
django_thumborize.egg-info/top_level.txt
thumborize/__init__.py
thumborize/conf.py
thumborize/crypto.py
thumborize/templatetags/__init__.py
thumborize/templatetags/thumborize.py