Metadata-Version: 1.1
Name: django-thumborize
Version: 1.0
Summary: Minimal interface for thumbor imaging service
Home-page: https://github.com/tpisani/django-thumborize
Author: Thiago Pisani
Author-email: pisani.thiago@gmail.com
License: BSD
Platform: UNKNOWN
Classifier: Environment :: Web Environment
Classifier: Framework :: Django
Classifier: Intended Audience :: Developers
Classifier: Operating System :: OS Independent
Classifier: Programming Language :: Python :: 2.7
